flask_core/__init__.py
flask_core/app.py
flask_core/config.py
flask_core/helpers.py
flask_core/auth/__init__.py
flask_core/auth/checker.py
flask_core/auth/cseauth.py
flask_core/auth/forwardedauth.py
flask_core/core/__init__.py
flask_core/core/models.py
flask_core/core/views.py
flask_core/core/templates/core/check.html
flask_core/core/templates/core/home.html
flask_core/core/templates/core/wipedb.html
flask_core/database/__init__.py
flask_core/database/database.py
flask_core/database/postgres.py
flask_core/flag/__init__.py
flask_core/middleware/AuthMiddleware.py
flask_core/middleware/FilterMiddleware.py
flask_core/middleware/IsolationMiddleware.py
flask_core/middleware/ReverseProxyMiddleware.py
flask_core/middleware/__init__.py
flask_core/middleware/handler.py
flask_core/templates/common/base.html
flask_core-2.9.0.dist-info/LICENCE.md
flask_core-2.9.0.dist-info/METADATA
flask_core-2.9.0.dist-info/WHEEL
flask_core-2.9.0.dist-info/top_level.txt
flask_core-2.9.0.dist-info/RECORD
