Metadata-Version: 2.1
Name: flask-core
Version: 2.9.0
Summary: A modular Flask core for CTF war-games, originally created for CS6443
Home-page: https://github.com/secedu/flask-core
Author: Carey Li, Sean Yeoh, Zain Afzal
Author-email: cs6443@cse.unsw.edu.au
License: UNKNOWN
Platform: UNKNOWN
Classifier: Programming Language :: Python :: 3
